faker_researcher_ids/__init__.py
faker_researcher_ids-0.1.0.dist-info/licenses/LICENSE
faker_researcher_ids-0.1.0.dist-info/WHEEL
faker_researcher_ids-0.1.0.dist-info/METADATA
faker_researcher_ids-0.1.0.dist-info/RECORD
