Metadata-Version: 2.4
Name: faker-researcher-ids
Version: 0.1.0
Summary: Fake researcher IDs in scientific databases and publication tracking systems
Author: Oleksandr Tislichenko
Author-email: Oleksandr Tislichenko <altis1024@gmail.com>
License-Expression: MIT
License-File: LICENSE
Classifier: Development Status :: 4 - Beta
Classifier: License :: OSI Approved :: MIT License
Classifier: Operating System :: OS Independent
Classifier: Programming Language :: Python :: 3
Requires-Dist: faker>=37.8.0
Requires-Python: >=3.13
